boat_ms/__init__.py
boat_ms/boat_opt.py
boat_ms/operation_registry.py
boat_ms/dynamic_ol/__init__.py
boat_ms/dynamic_ol/dynamical_system.py
boat_ms/fogm/__init__.py
boat_ms/fogm/mesm.py
boat_ms/fogm/pgdm.py
boat_ms/fogm/vfm.py
boat_ms/fogm/vsm.py
boat_ms/utils/__init__.py
boat_ms/utils/op_utils.py
boat_ms-1.0.1.dist-info/LICENSE
boat_ms-1.0.1.dist-info/METADATA
boat_ms-1.0.1.dist-info/WHEEL
boat_ms-1.0.1.dist-info/top_level.txt
boat_ms-1.0.1.dist-info/RECORD
