Metadata-Version: 2.1
Name: boat-ms
Version: 1.0.1
Summary: A Bilevel Optimization Toolkit in Python for Learning and Vision Tasks Based on MindSpore
Home-page: https://github.com/callous-youth/BOAT/tree/boat_ms
Author: Yaohua Liu, Xianghao Jiao, Risheng Liu
Author-email: liuyaohua.918@gmail.com
License: MIT
Keywords: Bilevel-optimization,Learning and vision,Python,Deep learning,MindSpore
Classifier: License :: OSI Approved :: MIT License
Classifier: Programming Language :: Python :: 3
Classifier: Programming Language :: Python :: 3.9
Classifier: Operating System :: OS Independent
Requires-Python: >=3.9.0
License-File: LICENSE
Requires-Dist: setuptools
Requires-Dist: numpy
Requires-Dist: tqdm
Requires-Dist: scikit-learn>=1.3
Requires-Dist: mindspore-dev
Requires-Dist: matplotlib
